setup.py
ldpy/__init__.py
ldpy/client.py
ldpy.egg-info/PKG-INFO
ldpy.egg-info/SOURCES.txt
ldpy.egg-info/dependency_links.txt
ldpy.egg-info/requires.txt
ldpy.egg-info/top_level.txt