Metadata-Version: 1.1
Name: ldpy
Version: 0.1.0
Summary: LDP Client for Python
Home-page: http://github.com/wikier/ldpy
Author: Sergio Fernandez
Author-email: sergio@wikier.org
License: Apache Software License 2.0
Download-URL: http://github.com/wikier/ldpy/releases
Keywords: python ldp linkeddata rdf marmotta
Platform: any
Classifier: Development Status :: 3 - Alpha
Classifier: Intended Audience :: Developers
Classifier: License :: OSI Approved :: Apache Software License
Classifier: Operating System :: OS Independent
Classifier: Programming Language :: Python :: 2
Classifier: Programming Language :: Python :: 3
Requires: rdflib
Requires: requests
